ouro_cache_fix/__init__.py
ouro_cache_fix/py.typed
ouro_cache_fix/universal_transformer_cache.py
ouro_cache_fix-0.1.0.dist-info/licenses/LICENSE
ouro_cache_fix-0.1.0.dist-info/METADATA
ouro_cache_fix-0.1.0.dist-info/WHEEL
ouro_cache_fix-0.1.0.dist-info/top_level.txt
ouro_cache_fix-0.1.0.dist-info/RECORD
