Metadata-Version: 2.4
Name: ouro-cache-fix
Version: 0.1.0
Summary: Custom cache implementation to fix KV cache bug in ByteDance/Ouro-1.4B
Author-email: Edwin Villacis <edwinvillacisa@yahoo.com>
License-Expression: MIT
Project-URL: Homepage, https://github.com/Antizana/ouro-cache-fix
Project-URL: Documentation, https://github.com/Antizana/ouro-cache-fix#readme
Project-URL: Repository, https://github.com/Antizana/ouro-cache-fix.git
Project-URL: Issues, https://github.com/Antizana/ouro-cache-fix/issues
Keywords: ouro,universal-transformer,cache,huggingface,transformers,llm,bug-fix,kv-cache
Classifier: Development Status :: 4 - Beta
Classifier: Intended Audience :: Developers
Classifier: Intended Audience :: Science/Research
Classifier: Topic :: Scientific/Engineering :: Artificial Intelligence
Classifier: Programming Language :: Python :: 3
Classifier: Programming Language :: Python :: 3.8
Classifier: Programming Language :: Python :: 3.9
Classifier: Programming Language :: Python :: 3.10
Classifier: Programming Language :: Python :: 3.11
Classifier: Programming Language :: Python :: 3.12
Classifier: Operating System :: OS Independent
Requires-Python: >=3.8
License-File: LICENSE
Requires-Dist: torch>=2.0.0
Requires-Dist: transformers>=4.36.0
Provides-Extra: dev
Requires-Dist: pytest>=7.0.0; extra == "dev"
Requires-Dist: pytest-cov>=4.0.0; extra == "dev"
Requires-Dist: black>=23.0.0; extra == "dev"
Requires-Dist: flake8>=6.0.0; extra == "dev"
Requires-Dist: mypy>=1.0.0; extra == "dev"
Provides-Extra: examples
Requires-Dist: peft>=0.7.0; extra == "examples"
Requires-Dist: datasets>=2.14.0; extra == "examples"
Requires-Dist: tqdm>=4.65.0; extra == "examples"
Dynamic: license-file
